[
  {
    "name": "Job Portal",
    "desc": "Full-Stack Job-portal for job finding and apply to the company",
    "image": "job",
    "category": "mern",
    "links": {
      "view": "#",
      "code": "https://github.com/akash-0078/Job_portal"
    }
  },
  {
    "name": "Gym Website",
    "desc": "A website For Gym membership and choose your own trainer .",
    "image": "gym",
    "category": "React js and next js",
    "links": {
      "view": "#",
      "code": "https://github.com/jigar-sable/sppu-prep-android"
    }
  },
  {
    "name": "Movie App",
    "desc": "App to search movies and watch it",
    "image": "newsboxandroid",
    "category": "react js and next js",
    "links": {
      "view": "#",
      "code": "https://github.com/jigar-sable/newsbox-android"
    }
  },
  {
    "name": "Portfolio",
    "desc": "Self profile site for reach ",
    "image": "weatherlyandroid",
    "category": "React",
    "links": {
     
      "code": "https://github.com/jigar-sable/weatherly-android"
    }
  },
  
  {
    "name": "Old Websites",
    "desc": "Bestwebs & ColorCoder. Two Years old websites memories. Simple with basic features.",
    "image": "oldsites",
    "category": "basicweb",
    "links": {
      "view": "#",
      "code": "#"
    }
  },
  {
    "name": "Resistor Color Codes",
    "desc": "Simply provides the color codes of resistors. Calculation information and about resistors.",
    "image": "resistercolor",
    "category": "basicweb",
    "links": {
      "view": "#",
      "code": "#"
    }
  },
  {
    "name": "KIA Info Website",
    "desc": "Basic KIA webpage displays the info about seltos product range. Specs and Image Gallery.",
    "image": "kiaweb",
    "category": "basicweb",
    "links": {
      "view": "#",
      "code": "#"
    }
  },
  {
    "name": "Burger Shop Dummy",
    "desc": "Basic burger shop webpage allow users to check menu and price. Dummy Order Form.",
    "image": "burgerweb",
    "category": "basicweb",
    "links": {
      "view": "#",
      "code": "#"
    }
  },
  {
    "name": "Indian Temples",
    "desc": "It shows temples of different sectors of India. as user clicks it will redirect to wiki of that temple for info.",
    "image": "templeweb",
    "category": "basicweb",
    "links": {
      "view": "#",
      "code": "#"
    }
  },
  {
    "name": "Indian Temples",
    "desc": "It shows temples of different sectors of India. as user clicks it will redirect to wiki of that temple for info.",
    "image": "templeweb",
    "category": "basicweb",
    "links": {
      "view": "#",
      "code": "#"
    }
  },
  {
    "name": "Indian Temples",
    "desc": "It shows temples of different sectors of India. as user clicks it will redirect to wiki of that temple for info.",
    "image": "templeweb",
    "category": "basicweb",
    "links": {
      "view": "#",
      "code": "#"
    }
  }
]
